{
	"name": "Json1",
	"properties": {
		"linkedServiceName": {
			"referenceName": "AzureDataLakeStorage_linkedservice",
			"type": "LinkedServiceReference"
		},
		"annotations": [],
		"type": "Json",
		"typeProperties": {
			"location": {
				"type": "AzureBlobFSLocation",
				"folderPath": "destination",
				"fileSystem": "mygen2container"
			}
		},
		"schema": {
			"type": "object",
			"properties": {
				"name": {
					"type": "string"
				},
				"email": {
					"type": "string"
				},
				"address": {
					"type": "string"
				},
				"phone": {
					"type": "string"
				},
				"website": {
					"type": "string"
				}
			}
		}
	}
}